optimation/__init__.py
optimation/core.py
optimation/logic.py
optimation/model.py
optimation/quantum.py
optimation/solver.py
optimation-2.2.dist-info/METADATA
optimation-2.2.dist-info/WHEEL
optimation-2.2.dist-info/top_level.txt
optimation-2.2.dist-info/RECORD
