Metadata-Version: 2.4
Name: optimation
Version: 2.2
Summary: Enhanced version 2.2 with variable modeling and optimation.
Home-page: https://github.com/yourusername/optimation
Author: Sourceduty
Author-email: Sourceduty <sourceduty@gmail.com>
Classifier: Programming Language :: Python :: 3
Classifier: License :: OSI Approved :: MIT License
Classifier: Operating System :: OS Independent
Requires-Python: >=3.6
Dynamic: author
Dynamic: home-page
Dynamic: requires-python
